docx_translate/__init__.py
docx_translate/version.json
docx_translate/bin/__init__.py
docx_translate/bin/main.py
docx_translate/core/__init__.py
docx_translate/core/translate.py
docx_translate/core/translator/__init__.py
docx_translate/core/translator/base.py
docx_translate/core/translator/google.py
docx_translate/util/__init__.py
docx_translate-1.0.1.dist-info/METADATA
docx_translate-1.0.1.dist-info/WHEEL
docx_translate-1.0.1.dist-info/entry_points.txt
docx_translate-1.0.1.dist-info/top_level.txt
docx_translate-1.0.1.dist-info/RECORD
